AUTHORS.rst
CONTRIBUTING.rst
HISTORY.rst
LICENSE
MANIFEST.in
README.rst
setup.cfg
setup.py
django_socket_server.egg-info/PKG-INFO
django_socket_server.egg-info/SOURCES.txt
django_socket_server.egg-info/dependency_links.txt
django_socket_server.egg-info/not-zip-safe
django_socket_server.egg-info/requires.txt
django_socket_server.egg-info/top_level.txt
socket_server/__init__.py
socket_server/exceptions.py
socket_server/models.py
socket_server/namespace.py
socket_server/server.py
socket_server/string.py
socket_server/management/__init__.py
socket_server/management/commands/__init__.py
socket_server/management/commands/start_socket.py
socket_server/migrations/0001_initial.py
socket_server/migrations/__init__.py
socket_server/static/socket_server/custom/js/client.js