Metadata-Version: 1.1
Name: django-socket-server
Version: 0.0.1
Summary: Django Socket Server
Home-page: https://github.com/CptLemming/django-socket-server
Author: Ashley Wilson
Author-email: scifilem@gmail.com
License: BSD
Keywords: django-socket-server
Platform: UNKNOWN
Classifier: Development Status :: 2 - Pre-Alpha
Classifier: Framework :: Django
Classifier: Intended Audience :: Developers
Classifier: License :: OSI Approved :: BSD License
Classifier: Natural Language :: English
Classifier: Programming Language :: Python :: 2
Classifier: Programming Language :: Python :: 2.6
Classifier: Programming Language :: Python :: 2.7
Classifier: Programming Language :: Python :: 3
Classifier: Programming Language :: Python :: 3.3
